MANIFEST.in
README.rst
setup.py
aliyun_python_sdk_linkface.egg-info/PKG-INFO
aliyun_python_sdk_linkface.egg-info/SOURCES.txt
aliyun_python_sdk_linkface.egg-info/dependency_links.txt
aliyun_python_sdk_linkface.egg-info/requires.txt
aliyun_python_sdk_linkface.egg-info/top_level.txt
aliyunsdklinkface/__init__.py
aliyunsdklinkface/request/__init__.py
aliyunsdklinkface/request/v20180720/CreateGroupRequest.py
aliyunsdklinkface/request/v20180720/DeleteDeviceAllGroupRequest.py
aliyunsdklinkface/request/v20180720/DeleteDeviceGroupRequest.py
aliyunsdklinkface/request/v20180720/DeleteFaceRequest.py
aliyunsdklinkface/request/v20180720/DeleteGroupRequest.py
aliyunsdklinkface/request/v20180720/LinkFaceRequest.py
aliyunsdklinkface/request/v20180720/QueryAddUserInfoRequest.py
aliyunsdklinkface/request/v20180720/QueryAllGroupsRequest.py
aliyunsdklinkface/request/v20180720/QueryAuthenticationRequest.py
aliyunsdklinkface/request/v20180720/QueryFaceRequest.py
aliyunsdklinkface/request/v20180720/QueryGroupUsersRequest.py
aliyunsdklinkface/request/v20180720/QueryLicensesRequest.py
aliyunsdklinkface/request/v20180720/QuerySyncPicScheduleRequest.py
aliyunsdklinkface/request/v20180720/RegisterFaceRequest.py
aliyunsdklinkface/request/v20180720/SearchFaceRequest.py
aliyunsdklinkface/request/v20180720/SyncFacePicturesRequest.py
aliyunsdklinkface/request/v20180720/UnlinkFaceRequest.py
aliyunsdklinkface/request/v20180720/UpdateFaceRequest.py
aliyunsdklinkface/request/v20180720/__init__.py